mosaicking/__init__.py
mosaicking/_version.py
mosaicking/calibration.py
mosaicking/mosaic.py
mosaicking/preprocessing.py
mosaicking/registration.py
mosaicking/splitter.py
mosaicking/transformations.py
mosaicking/utils.py
mosaicking/core/__init__.py
mosaicking/core/db.py
mosaicking/core/helpers.py
mosaicking/core/interface.py
mosaicking/resources/schema.sql
mosaic_library-2.0.1.dist-info/LICENSE
mosaic_library-2.0.1.dist-info/METADATA
mosaic_library-2.0.1.dist-info/WHEEL
mosaic_library-2.0.1.dist-info/entry_points.txt
mosaic_library-2.0.1.dist-info/top_level.txt
mosaic_library-2.0.1.dist-info/RECORD
