Metadata-Version: 2.2
Name: mosaic-library
Version: 2.0.1
Summary: A python library for manipulating images for underwater mosaicking applications.
Author-email: Fletcher Thompson <fletho@dtu.dk>
Project-URL: Homepage, https://gitlab.gbar.dtu.dk/dtu-aqua-observation-technology/camera/mosaic-library
Project-URL: Bug Tracker, https://gitlab.gbar.dtu.dk/dtu-aqua-observation-technology/camera/mosaic-library/-/issues
Project-URL: Github, https://github.com/DTUAqua-ObsTek/mosaic-library
Project-URL: Bug Tracker Github, https://github.com/DTUAqua-ObsTek/mosaic-library/issues
Classifier: Programming Language :: Python :: 3.10
Classifier: Programming Language :: Python :: 3.11
Classifier: Programming Language :: Python :: 3.12
Classifier: License :: OSI Approved :: MIT License
Classifier: Operating System :: OS Independent
Requires-Python: >=3.10
License-File: LICENSE
Requires-Dist: networkx
Requires-Dist: pandas
Requires-Dist: pyyaml
Requires-Dist: scikit-learn
Requires-Dist: scipy
Requires-Dist: shapely
Provides-Extra: opencv
Requires-Dist: opencv-contrib-python; extra == "opencv"
